odoo/addons/ddmrp_chatter/README.rst
odoo/addons/ddmrp_chatter/__init__.py
odoo/addons/ddmrp_chatter/__manifest__.py
odoo/addons/ddmrp_chatter/i18n/ddmrp_chatter.pot
odoo/addons/ddmrp_chatter/i18n/es.po
odoo/addons/ddmrp_chatter/i18n/it.po
odoo/addons/ddmrp_chatter/models/__init__.py
odoo/addons/ddmrp_chatter/models/stock_buffer.py
odoo/addons/ddmrp_chatter/readme/CONTRIBUTORS.rst
odoo/addons/ddmrp_chatter/readme/DESCRIPTION.rst
odoo/addons/ddmrp_chatter/readme/HISTORY.rst
odoo/addons/ddmrp_chatter/static/description/icon.png
odoo/addons/ddmrp_chatter/static/description/index.html
odoo/addons/ddmrp_chatter/views/ddmrp_buffer_view.xml
odoo14_addon_ddmrp_chatter-14.0.1.0.1.dist-info/METADATA
odoo14_addon_ddmrp_chatter-14.0.1.0.1.dist-info/WHEEL
odoo14_addon_ddmrp_chatter-14.0.1.0.1.dist-info/top_level.txt
odoo14_addon_ddmrp_chatter-14.0.1.0.1.dist-info/RECORD
